coveo_stew/__init__.py
coveo_stew/ci/__init__.py
coveo_stew/ci/any_runner.py
coveo_stew/ci/black_runner.py
coveo_stew/ci/config.py
coveo_stew/ci/mypy_runner.py
coveo_stew/ci/poetry_runners.py
coveo_stew/ci/pytest_runner.py
coveo_stew/ci/reporting.py
coveo_stew/ci/runner.py
coveo_stew/ci/runner_status.py
coveo_stew/ci/stew_runners.py
coveo_stew/commands.py
coveo_stew/config.py
coveo_stew/discovery.py
coveo_stew/environment.py
coveo_stew/exceptions.py
coveo_stew/metadata/__init__.py
coveo_stew/metadata/poetry_api.py
coveo_stew/metadata/python_api.py
coveo_stew/metadata/stew_api.py
coveo_stew/offline_publish.py
coveo_stew/package_resources/mypy.ini
coveo_stew/piptools/__init__.py
coveo_stew/poetry_backward_compatibility.py
coveo_stew/poetry_plugin.py
coveo_stew/presets/__init__.py
coveo_stew/presets/presets.py
coveo_stew/presets/presets_list.py
coveo_stew/py.typed
coveo_stew/pydev.py
coveo_stew/stew.py
coveo_stew/ui/__init__.py
coveo_stew/ui/click/__init__.py
coveo_stew/ui/click/cli.py
coveo_stew/ui/poetry/__init__.py
coveo_stew/ui/poetry/base_command.py
coveo_stew/ui/poetry/build_command.py
coveo_stew/ui/poetry/bump_command.py
coveo_stew/ui/poetry/check_outdated_command.py
coveo_stew/ui/poetry/ci_command.py
coveo_stew/ui/poetry/fix_outdated_command.py
coveo_stew/ui/poetry/fresh_eggs_command.py
coveo_stew/ui/poetry/locate_command.py
coveo_stew/ui/poetry/presets_list.py
coveo_stew/ui/poetry/pull_dev_requirements_command.py
coveo_stew/ui/poetry/refresh_command.py
coveo_stew/ui/poetry/stew_command.py
coveo_stew/ui/poetry/version_command.py
coveo_stew/utils.py
coveo_stew-4.1.5.dist-info/METADATA
coveo_stew-4.1.5.dist-info/WHEEL
coveo_stew-4.1.5.dist-info/entry_points.txt
coveo_stew-4.1.5.dist-info/licenses/LICENSE
coveo_stew-4.1.5.dist-info/licenses/LICENSE.md
coveo_stew-4.1.5.dist-info/RECORD
