Metadata-Version: 2.4
Name: coveo-stew
Version: 4.1.5
Summary: Opinionated python packaging and development utilities
License: Apache-2.0
License-File: LICENSE
License-File: LICENSE.md
Keywords: packaging,poetry,plugin,ci,tests
Author: Jonathan Piché
Author-email: tools@coveo.com
Requires-Python: >=3.10,<4
Classifier: License :: OSI Approved :: Apache Software License
Classifier: Programming Language :: Python :: 3
Classifier: Programming Language :: Python :: 3.10
Classifier: Programming Language :: Python :: 3.11
Classifier: Programming Language :: Python :: 3.12
Classifier: Programming Language :: Python :: 3.13
Classifier: Programming Language :: Python :: 3.14
Requires-Dist: click (>=8.2)
Requires-Dist: coveo-functools (>=2)
Requires-Dist: coveo-itertools (>=2)
Requires-Dist: coveo-styles (>=2)
Requires-Dist: coveo-systools (>=3.0.1)
Requires-Dist: importlib-resources (>=6)
Requires-Dist: junit-xml (>=1)
Requires-Dist: packaging (>=25)
Requires-Dist: poetry (>=2)
Requires-Dist: poetry-plugin-export (>=1)
Requires-Dist: setuptools (>=80)
Requires-Dist: toml (>=0.10)
Requires-Dist: tomlkit (>=0.13)
Project-URL: Repository, https://github.com/coveo/stew
